gdsfactory/__init__.py
gdsfactory/_cell.py
gdsfactory/_deprecation.py
gdsfactory/add_padding.py
gdsfactory/add_pins.py
gdsfactory/add_ports.py
gdsfactory/boolean.py
gdsfactory/cli.py
gdsfactory/component.py
gdsfactory/component_layout.py
gdsfactory/config.py
gdsfactory/constants.py
gdsfactory/containers.py
gdsfactory/cross_section.py
gdsfactory/difftest.py
gdsfactory/difftest_git.py
gdsfactory/font.py
gdsfactory/functions.py
gdsfactory/get_factories.py
gdsfactory/get_netlist.py
gdsfactory/grid.py
gdsfactory/install.py
gdsfactory/name.py
gdsfactory/pack.py
gdsfactory/path.py
gdsfactory/pdk.py
gdsfactory/port.py
gdsfactory/py.typed
gdsfactory/schematic.py
gdsfactory/serialization.py
gdsfactory/snap.py
gdsfactory/symbols.py
gdsfactory/typings.py
gdsfactory/utils.py
gdsfactory/watch.py
gdsfactory/write_cells.py
gdsfactory/components/__init__.py
gdsfactory/components/analog/__init__.py
gdsfactory/components/analog/inductors.py
gdsfactory/components/analog/interdigital_capacitor.py
gdsfactory/components/analog/microstrip.py
gdsfactory/components/bends/__init__.py
gdsfactory/components/bends/bend_circular.py
gdsfactory/components/bends/bend_circular_heater.py
gdsfactory/components/bends/bend_euler.py
gdsfactory/components/bends/bend_s.py
gdsfactory/components/containers/__init__.py
gdsfactory/components/containers/add_fiber_array_optical_south_electrical_north.py
gdsfactory/components/containers/add_termination.py
gdsfactory/components/containers/add_trenches.py
gdsfactory/components/containers/array_component.py
gdsfactory/components/containers/component_sequence.py
gdsfactory/components/containers/copy_layers.py
gdsfactory/components/containers/extend_ports_list.py
gdsfactory/components/containers/extension.py
gdsfactory/components/containers/pack_doe.py
gdsfactory/components/containers/splitter_chain.py
gdsfactory/components/containers/splitter_tree.py
gdsfactory/components/couplers/__init__.py
gdsfactory/components/couplers/coupler.py
gdsfactory-9.33.0.dist-info/entry_points.txt
gdsfactory-9.33.0.dist-info/licenses/LICENSE
gdsfactory-9.33.0.dist-info/WHEEL
gdsfactory-9.33.0.dist-info/METADATA
gdsfactory-9.33.0.dist-info/RECORD
