Metadata-Version: 2.4
Name: gdsfactory
Version: 9.33.0
Summary: python library to generate GDS layouts
Keywords: eda,photonics,python
Author-email: gdsfactory community <contact@gdsfactory.com>
Requires-Python: >=3.11,<3.14
Classifier: Programming Language :: Python :: 3.11
Classifier: Programming Language :: Python :: 3.12
Classifier: Programming Language :: Python :: 3.13
Classifier: Operating System :: OS Independent
License-File: LICENSE
Requires-Dist: jinja2<4
Requires-Dist: loguru<1
Requires-Dist: matplotlib<4
Requires-Dist: numpy
Requires-Dist: orjson<4
Requires-Dist: pandas
Requires-Dist: pydantic>=2
Requires-Dist: pydantic-settings<3
Requires-Dist: pydantic-extra-types<3
Requires-Dist: pyyaml
Requires-Dist: qrcode
Requires-Dist: rectpack<1
Requires-Dist: rich<15
Requires-Dist: scipy<2
Requires-Dist: shapely<3
Requires-Dist: toolz<2
Requires-Dist: types-PyYAML
Requires-Dist: typer<1
Requires-Dist: kfactory[ipy]>=2.2,<2.4
Requires-Dist: watchdog<7
Requires-Dist: freetype-py
Requires-Dist: mapbox_earcut
Requires-Dist: networkx
Requires-Dist: scikit-image
Requires-Dist: trimesh>=4.4.1
Requires-Dist: ipykernel
Requires-Dist: attrs
Requires-Dist: graphviz
Requires-Dist: pyglet<3
Requires-Dist: typing-extensions
Requires-Dist: pygit2
Requires-Dist: natsort
Requires-Dist: kweb>=1.1.9,<2.1 ; extra == "cad"
Requires-Dist: codeflash ; extra == "dev"
Requires-Dist: ipykernel ; extra == "dev"
Requires-Dist: jupyterlab ; extra == "dev"
Requires-Dist: jsondiff ; extra == "dev"
Requires-Dist: jsonschema ; extra == "dev"
Requires-Dist: pre-commit ; extra == "dev"
Requires-Dist: pylsp-mypy ; extra == "dev"
Requires-Dist: pytest ; extra == "dev"
Requires-Dist: pytest-cov ; extra == "dev"
Requires-Dist: pytest_regressions ; extra == "dev"
Requires-Dist: types-PyYAML ; extra == "dev"
Requires-Dist: types-cachetools ; extra == "dev"
Requires-Dist: pytest-github-actions-annotate-failures ; extra == "dev"
Requires-Dist: pytest-randomly ; extra == "dev"
Requires-Dist: pytest-xdist ; extra == "dev"
Requires-Dist: ty ; extra == "dev"
Requires-Dist: autodoc_pydantic>=2.0.1,<3 ; extra == "docs"
Requires-Dist: jupytext ; extra == "docs"
Requires-Dist: jupyter-book>=0.15.1,<1.1 ; extra == "docs"
Requires-Dist: plotly ; extra == "docs"
Requires-Dist: Sphinx==7.4.7 ; extra == "docs"
Requires-Dist: gplugins[devsim, femwell, gmsh, meow, sax, schematic, tidy3d]>=1.1,<3.0 ; extra == "full"
Requires-Dist: scikit-rf ; extra == "full"
Requires-Dist: omegaconf ; extra == "full"
Requires-Dist: autograd ; extra == "full"
Requires-Dist: ruff>=0.8.3 ; extra == "maintainer"
Requires-Dist: doc8 ; extra == "maintainer"
Requires-Dist: xdoctest ; extra == "maintainer"
Requires-Dist: mypy ; extra == "maintainer"
Requires-Dist: tbump ; extra == "maintainer"
Requires-Dist: autotyping ; extra == "maintainer"
Requires-Dist: towncrier ; extra == "maintainer"
Provides-Extra: cad
Provides-Extra: dev
Provides-Extra: docs
Provides-Extra: full
Provides-Extra: maintainer
